markingpy/__init__.py
markingpy/cases.py
markingpy/cli.py
markingpy/compiler.py
markingpy/config.py
markingpy/execution.py
markingpy/exercise.py
markingpy/exercises.py
markingpy/finders.py
markingpy/grader.py
markingpy/linter.py
markingpy/linters.py
markingpy/magic.py
markingpy/markscheme.py
markingpy/storage.py
markingpy/submission.py
markingpy/syntax.py
markingpy/users.py
markingpy/utils.py
markingpy/data/markingpy.conf
markingpy/data/scheme.py
markingpy-1.0.0.dist-info/LICENSE
markingpy-1.0.0.dist-info/METADATA
markingpy-1.0.0.dist-info/WHEEL
markingpy-1.0.0.dist-info/entry_points.txt
markingpy-1.0.0.dist-info/top_level.txt
markingpy-1.0.0.dist-info/RECORD
