Metadata-Version: 2.1
Name: markingpy
Version: 1.0.0
Summary: Program for automatic grading of Python code.
Home-page: https://markingpy.readthedocs.io/en/latest/index.html
Author: Sam Morley
Author-email: sam@inakleinbottle.com
License: UNKNOWN
Platform: UNKNOWN
Classifier: Programming Language :: Python :: 3
Classifier: Programming Language :: Python :: 3.6
Classifier: Programming Language :: Python :: 3.7
Classifier: License :: OSI Approved :: GNU General Public License v3 (GPLv3)
Classifier: Operating System :: OS Independent
Requires-Python: >=3.6
Requires-Dist: pylint
